pydeevo/__init__.py
pydeevo/py.typed
pydeevo/evolution/__init__.py
pydeevo/evolution/architecture_search.py
pydeevo/integration/__init__.py
pydeevo/integration/pydeevo.py
pydeevo/models/__init__.py
pydeevo/models/base.py
pydeevo/optimization/__init__.py
pydeevo/optimization/optuna_optimizer.py
pydeevo/training/__init__.py
pydeevo/training/callbacks.py
pydeevo/training/trainer.py
pydeevo/utils/__init__.py
pydeevo/utils/data.py
pydeevo/utils/database.py
pydeevo/utils/distributed.py
pydeevo/utils/export.py
pydeevo/utils/helpers.py
pydeevo/utils/profiling.py
pydeevo-0.0.1.dist-info/METADATA
pydeevo-0.0.1.dist-info/WHEEL
pydeevo-0.0.1.dist-info/RECORD
