Metadata-Version: 2.4
Name: pydeevo
Version: 0.0.1
Summary: PyDeevo is a comprehensive framework for neural network architecture search, hyperparameter optimization, and efficient training. It integrates modern deep learning tools into a cohesive, modular ecosystem:  PyTorch Lightning: For structured, scalable deep learning Optuna: For efficient hyperparameter optimization PyGAD: For evolutionary architecture search Polars & DuckDB: For high-performance data processing and analytics Advanced Utils: For distributed training, profiling, and deploy
Author: Björn Bethge
Requires-Python: >=3.13
Requires-Dist: altair[all]>=5.5.0
Requires-Dist: duckdb>=1.2.2
Requires-Dist: lightning>=2.5.1
Requires-Dist: optuna>=4.2.1
Requires-Dist: polars>=1.27.0
Requires-Dist: pygad>=3.4.0
Requires-Dist: sqlglot>=26.12.1
Requires-Dist: usearch>=2.17.6
Requires-Dist: zenml>=0.80.2
